storekiss/__init__.py
storekiss/crud.py
storekiss/crud.py.bak
storekiss/errors.py
storekiss/exceptions.py
storekiss/export_import.py
storekiss/firestore.py
storekiss/geopoint.py
storekiss/litestore.py
storekiss/reference.py
storekiss/validation.py
storekiss-0.2.8.dist-info/LICENSE
storekiss-0.2.8.dist-info/METADATA
storekiss-0.2.8.dist-info/WHEEL
storekiss-0.2.8.dist-info/RECORD
