Metadata-Version: 2.3
Name: storekiss
Version: 0.2.8
Summary: A CRUD interface library with SQLite storage
Author: Devin AI
Author-email: devin-ai-integration[bot]@users.noreply.github.com
Requires-Python: >=3.8,<4.0
Classifier: Programming Language :: Python :: 3
Classifier: Programming Language :: Python :: 3.8
Classifier: Programming Language :: Python :: 3.9
Classifier: Programming Language :: Python :: 3.10
Classifier: Programming Language :: Python :: 3.11
Classifier: Programming Language :: Python :: 3.12
Classifier: Programming Language :: Python :: 3.13
